{
  "userData": [
    {
      "id": 1,
      "title": "trim dress",
      "price": 109.95,
      "image": "https://multikart-react-reactpixelstrap.vercel.app/assets/images/pro3/6.jpg",
      "rating": {
        "rate": 3.9,
        "count": 120
      }
    },
    {
      "id": 2,
      "title": "belted dress",
      "price": 109.95,
      "image": "https://multikart-react-reactpixelstrap.vercel.app/assets/images/pro3/4.jpg",
      "rating": {
        "rate": 3.9,
        "count": 120
      }
    },
    {
      "id": 3,
      "title": "fitted dress",
      "price": 109.95,
      "image": "https://multikart-react-reactpixelstrap.vercel.app/assets/images/pro3/2.jpg",
      "rating": {
        "rate": 3.9,
        "count": 120
      }
    },
    {
      "id": 4,
      "title": "belted top",
      "price": 109.95,
      "image": "https://multikart-react-reactpixelstrap.vercel.app/assets/images/pro3/7.jpg",
      "rating": {
        "rate": 3.9,
        "count": 120
      }
    },
    {
      "id": 5,
      "title": "trim dress",
      "price": 109.95,
      "image": "https://multikart-react-reactpixelstrap.vercel.app/assets/images/pro3/10.jpg",
      "rating": {
        "rate": 3.9,
        "count": 120
      }
    },
    {
      "id": 6,
      "title": "trim dress",
      "price": 109.95,
      "image": "https://multikart-react-reactpixelstrap.vercel.app/assets/images/pro3/12.jpg",
      "rating": {
        "rate": 3.9,
        "count": 120
      }
    },
    {
      "id": 7,
      "title": "trim dress",
      "price": 109.95,
      "image": "https://multikart-react-reactpixelstrap.vercel.app/assets/images/pro3/16.jpg",
      "rating": {
        "rate": 3.9,
        "count": 120
      }
    },
    {
      "id": 8,
      "title": "trim dress",
      "price": 109.95,
      "image": "https://multikart-react-reactpixelstrap.vercel.app/assets/images/pro3/9.jpg",
      "rating": {
        "rate": 3.9,
        "count": 120
      }
    },
    {
      "id": 9,
      "title": "trim dress",
      "price": 109.95,
      "image": "https://multikart-react-reactpixelstrap.vercel.app/assets/images/pro3/5.jpg",
      "rating": {
        "rate": 3.9,
        "count": 120
      }
    },
    {
      "id": 10,
      "title": "trim dress",
      "price": 109.95,
      "image": "https://multikart-react-reactpixelstrap.vercel.app/assets/images/pro3/14.jpg",
      "rating": {
        "rate": 3.9,
        "count": 120
      }
      }, {
        "id": 11,
        "title": "trim dress",
        "price": 109.95,
        "image": "https://multikart-react-reactpixelstrap.vercel.app/assets/images/pro3/8.jpg",
      "rating": {
        "rate": 3.9,
        "count": 120
      }
    }, {
      "id": 12,
      "title": "trim dress",
      "price": 109.95,
      "image": "https://multikart-react-reactpixelstrap.vercel.app/assets/images/pro3/22.jpg",
      "rating": {
        "rate": 3.9,
        "count": 120
      }
    }
  ],
  "furniture": [
    {
      "id": 13,
      "title": "arm chair",
      "price": 201,
      "image": "https://multikart-react-reactpixelstrap.vercel.app/assets/images/furniture/product/1.jpg",
      "rating": {
        "rate": 3.9,
        "count": 120
      }
    },
    {
      "id": 14,
      "title": "oak Finish chair",
      "price": 475.60,
      "image": "https://multikart-react-reactpixelstrap.vercel.app/assets/images/furniture/product/3.jpg",
      "rating": {
        "rate": 3.9,
        "count": 120
      }
    },
    {
      "id": 15,
      "title": "wooden chair",
      "price": 345.50,
      "image": "https://multikart-react-reactpixelstrap.vercel.app/assets/images/furniture/product/7.jpg",
      "rating": {
        "rate": 3.9,
        "count": 120
      }
    },
    {
      "id": 16,
      "title": "Metal Table Lamp",
      "price": 295,
      "image": "https://multikart-react-reactpixelstrap.vercel.app/assets/images/furniture/product/19.jpg",
      "rating": {
        "rate": 3.9,
        "count": 120
      }
    },
    {
      "id": 17,
      "title": " Wood End Table",
      "price": 500,
      "image": "https://multikart-react-reactpixelstrap.vercel.app/assets/images/furniture/product/4.jpg",
      "rating": {
        "rate": 3.9,
        "count": 120
      }
    },
    {
      "id": 18,
      "title": "Lounge Chai",
      "price": 450,
      "image":"https://multikart-react-reactpixelstrap.vercel.app/assets/images/furniture/product/5.jpg",
      "rating": {
        "rate": 3.9,
        "count": 120
      }
    },
    {
      "id": 19,
      "title": "Rocking Chai",
      "price": 355.5,
      "image": "https://multikart-react-reactpixelstrap.vercel.app/assets/images/furniture/product/8.jpg",
      "rating": {
        "rate": 3.9,
        "count": 120
      }
    },
    {
      "id": 20,
      "title": "Barrel Chai",
      "price": 200,
      "image": "https://multikart-react-reactpixelstrap.vercel.app/assets/images/furniture/product/2.jpg",
      "rating": {
        "rate": 3.9,
        "count": 120
      }
    }
  ],
  "vegetable": [
    {
      "id": 21,
      "title": "Beetroot",
      "price": 31.50,
      "image": "https://multikart-react-reactpixelstrap.vercel.app/assets/images/vegetables/pro/1.jpg",
      "rating": {
        "rate": 4.0,
        "count": 120
      }
    },
    {
      "id": 22,
      "title": "Cabbage",
      "price": 20.00,
      "image": "https://multikart-react-reactpixelstrap.vercel.app/assets/images/vegetables/pro/2.jpg",
      "rating": {
        "rate": 3.9,
        "count": 120
      }
    },
    {
      "id": 23,
      "title": "Onion",
      "price": 27.55,
      "image": "https://multikart-react-reactpixelstrap.vercel.app/assets/images/vegetables/pro/3.jpg",
      "rating": {
        "rate": 3.9,
        "count": 120
      }
    },
    {
      "id": 24,
      "title": "Brinjal",
      "price": 29.60,
      "image": "https://multikart-react-reactpixelstrap.vercel.app/assets/images/vegetables/pro/4.jpg",
      "rating": {
        "rate": 3.9,
        "count": 120
      }
    },
    {
      "id": 25,
      "title": " Cucumber",
      "price": 44.22,
      "image": "https://multikart-react-reactpixelstrap.vercel.app/assets/images/vegetables/pro/5.jpg",
      "rating": {
        "rate": 3.9,
        "count": 120
      }
    },
    {
      "id": 26,
      "title": "Tomato",
      "price": 40.00,
      "image":"https://multikart-react-reactpixelstrap.vercel.app/assets/images/vegetables/pro/6.jpg",
      "rating": {
        "rate": 3.9,
        "count": 120
      }
    }
  ]

}